fxmacrodata/__init__.py
fxmacrodata/async_client.py
fxmacrodata/client.py
fxmacrodata/exceptions.py
fxmacrodata/utils.py
fxmacrodata-0.1.0.dist-info/licenses/LICENSE
fxmacrodata-0.1.0.dist-info/METADATA
fxmacrodata-0.1.0.dist-info/WHEEL
fxmacrodata-0.1.0.dist-info/top_level.txt
fxmacrodata-0.1.0.dist-info/RECORD
