Metadata-Version: 2.4
Name: fxmacrodata
Version: 0.1.0
Summary: Python client for the FXMacroData API, providing forex macroeconomic data for traders, quants, and analysts.
Author-email: FXMacroData <info@fxmacrodata.com>
License: MIT
Project-URL: Homepage, https://fxmacrodata.com/?utm_source=pypi&utm_medium=package&utm_campaign=python_sdk
Project-URL: Documentation, https://fxmacrodata.com/api/docs?utm_source=pypi&utm_medium=package&utm_campaign=python_sdk
Project-URL: Source, https://github.com/fxmacrodata/fxmacrodata
Project-URL: Issues, https://github.com/fxmacrodata/fxmacrodata
Keywords: forex,macro data,macroeconomics,trading,quant,economic indicators,fxmacrodata,rapidapi
Requires-Python: >=3.9
License-File: LICENSE
Requires-Dist: requests>=2.28
Requires-Dist: aiohttp>=3.8
Provides-Extra: dev
Requires-Dist: pytest>=8.0; extra == "dev"
Requires-Dist: pytest-mock>=3.10; extra == "dev"
Requires-Dist: python-dotenv>=1.1; extra == "dev"
Requires-Dist: python-semantic-release>=7.23; extra == "dev"
Requires-Dist: twine>=4.0; extra == "dev"
Requires-Dist: build>=1.0; extra == "dev"
Requires-Dist: ruff>=0.0; extra == "dev"
Requires-Dist: mypy>=1.5; extra == "dev"
Requires-Dist: black>=24.0; extra == "dev"
Requires-Dist: types-requests>=2.28; extra == "dev"
Dynamic: license-file
